cellphonedb/__init__.py
cellphonedb/src/__init__.py
cellphonedb/src/core/__init__.py
cellphonedb/src/core/core_logger.py
cellphonedb/src/core/exceptions/AllCountsFilteredException.py
cellphonedb/src/core/exceptions/DatabaseCreationException.py
cellphonedb/src/core/exceptions/EmptyResultException.py
cellphonedb/src/core/exceptions/MissingRequiredArgumentsException.py
cellphonedb/src/core/exceptions/NoComplexException.py
cellphonedb/src/core/exceptions/ParseCountsException.py
cellphonedb/src/core/exceptions/ProcessMetaException.py
cellphonedb/src/core/exceptions/ThresholdValueException.py
cellphonedb/src/core/exceptions/__init__.py
cellphonedb/src/core/generators/__init__.py
cellphonedb/src/core/generators/complex_generator.py
cellphonedb/src/core/generators/gene_generator.py
cellphonedb/src/core/generators/generator_helper.py
cellphonedb/src/core/generators/protein_generator.py
cellphonedb/src/core/methods/__init__.py
cellphonedb/src/core/methods/cpdb_analysis_method.py
cellphonedb/src/core/methods/cpdb_degs_analysis_method.py
cellphonedb/src/core/methods/cpdb_statistical_analysis_complex_method.py
cellphonedb/src/core/methods/cpdb_statistical_analysis_helper.py
cellphonedb/src/core/methods/cpdb_statistical_analysis_method.py
cellphonedb/src/core/models/__init__.py
cellphonedb/src/core/models/complex/__init__.py
cellphonedb/src/core/models/complex/complex_helper.py
cellphonedb/src/core/models/interaction/__init__.py
cellphonedb/src/core/preprocessors/__init__.py
cellphonedb/src/core/preprocessors/counts_preprocessors.py
cellphonedb/src/core/preprocessors/method_preprocessors.py
cellphonedb/src/core/utils/__init__.py
cellphonedb/src/core/utils/cellsign.py
cellphonedb/src/core/utils/subsampler.py
cellphonedb/src/exceptions/MissingRequiredColumns.py
cellphonedb/src/exceptions/NoReleasesException.py
cellphonedb/src/exceptions/NotADataFrameException.py
cellphonedb/src/exceptions/ParseMetaException.py
cellphonedb/src/exceptions/ReadFileException.py
cellphonedb-5.0.0.dist-info/METADATA
cellphonedb-5.0.0.dist-info/WHEEL
cellphonedb-5.0.0.dist-info/RECORD
