Metadata-Version: 2.1
Name: cellphonedb
Version: 5.0.0
Summary: Inferring cell-cell communication.
Home-page: https://github.com/ventolab/cellphonedb
License: MIT
Author: The CellPhoneDB development team
Author-email: contact@cellphonedb.org
Requires-Python: >=3.8
Classifier: Development Status :: 5 - Production/Stable
Classifier: Intended Audience :: Science/Research
Classifier: License :: OSI Approved :: MIT License
Classifier: Natural Language :: English
Classifier: Operating System :: MacOS :: MacOS X
Classifier: Operating System :: Microsoft :: Windows
Classifier: Operating System :: POSIX :: Linux
Classifier: Programming Language :: Python :: 3
Classifier: Programming Language :: Python :: 3.8
Classifier: Programming Language :: Python :: 3.9
Classifier: Programming Language :: Python :: 3.10
Classifier: Programming Language :: Python :: 3.11
Classifier: Topic :: Scientific/Engineering :: Bio-Informatics
Provides-Extra: dev
Requires-Dist: anndata (>=0.8)
Requires-Dist: black (>=22.3) ; extra == "dev"
Requires-Dist: geosketch (>=1.2)
Requires-Dist: isort (>=5.7) ; extra == "dev"
Requires-Dist: ktplotspy (>=0.1.4)
Requires-Dist: numpy (>=1.21.6)
Requires-Dist: numpy-groupies (>=0.9.15)
Requires-Dist: pandas (>=1.5.0)
Requires-Dist: requests (>=2.25.0)
Requires-Dist: scanpy (>=1.9.1)
Requires-Dist: scikit-learn (>=1.2.2)
Requires-Dist: tqdm (>=4.3,<5.0)
Project-URL: Documentation, https://github.com/ventolab/cellphonedb
